LICENSE.txt
MANIFEST.in
README.rst
Tool.py
setup.py
yxtestlib666.egg-info/PKG-INFO
yxtestlib666.egg-info/SOURCES.txt
yxtestlib666.egg-info/dependency_links.txt
yxtestlib666.egg-info/top_level.txt