Metadata-Version: 2.1
Name: yxtestlib666
Version: 1.0.1
Summary: this is a niubi lib
Home-page: https://github.com/wangshunzi/Python_code
Author: yx
Author-email: 1063387453@qq.com
License: MIT
License-File: LICENSE.txt
